ovtp/__init__.py
ovtp/__main__.py
ovtp/client/__init__.py
ovtp/client/config.py
ovtp/client/main.py
ovtp/client/ovtp_client.py
ovtp/server/__init__.py
ovtp/server/add_auth_keys.py
ovtp/server/config.py
ovtp/server/keys_conv.py
ovtp/server/main.py
ovtp/server/ovtp_server.py
ovtp/server/saved_key.py
ovtp/server/func/__init__.py
ovtp/server/func/check_key.py
ovtp-1.0.6.4.dist-info/.gitignore
ovtp-1.0.6.4.dist-info/LICENSE.txt
ovtp-1.0.6.4.dist-info/METADATA
ovtp-1.0.6.4.dist-info/WHEEL
ovtp-1.0.6.4.dist-info/top_level.txt
ovtp-1.0.6.4.dist-info/RECORD
