Metadata-Version: 2.1
Name: ovtp
Version: 1.0.6.4
Summary: Over Transfer Protocol
Home-page: 
Author: Dmitry Yakovlev
Author-email: info@overhosting.ru
Requires-Python: >=3.7
License-File: LICENSE.txt
Requires-Dist: rsa
Requires-Dist: ovcrypt
Requires-Dist: oe_common
Requires-Dist: ov_aes_cipher
Requires-Dist: ovcfg
